hello_pypi_github.py
hello_pypi_github-1.1.0.dist-info/METADATA
hello_pypi_github-1.1.0.dist-info/WHEEL
hello_pypi_github-1.1.0.dist-info/top_level.txt
hello_pypi_github-1.1.0.dist-info/RECORD
