Metadata-Version: 2.1
Name: hello-pypi-github
Version: 1.1.0
Summary: A utility just to test the pypi distribution flow with github actions.
Home-page: https://github.com/danialmalik/hello-pypi-github
Author: Danial Malik
Author-email: danialmalik@321.com
License: UNKNOWN
Platform: UNKNOWN
